hij5_topdesk_api/__init__.py
hij5_topdesk_api/topdesk.py
hij5_topdesk_api/exceptions/__init__.py
hij5_topdesk_api/exceptions/exceptions.py
hij5_topdesk_api-1.0.2.dist-info/LICENSE
hij5_topdesk_api-1.0.2.dist-info/METADATA
hij5_topdesk_api-1.0.2.dist-info/WHEEL
hij5_topdesk_api-1.0.2.dist-info/top_level.txt
hij5_topdesk_api-1.0.2.dist-info/RECORD
