Metadata-Version: 2.1
Name: hij5-topdesk-api
Version: 1.0.2
Summary: A package to interact with the (currently 3.3.0) newest version of Topdesk.
Home-page: UNKNOWN
Author: Jeroen van der Laan
Author-email: j.vanderlaan@hij5.nl
License: UNKNOWN
Platform: UNKNOWN
Classifier: Programming Language :: Python :: 3
Classifier: License :: OSI Approved :: MIT License
Classifier: Operating System :: OS Independent
Requires-Python: >=3.6
License-File: LICENSE
